LICENSE
MANIFEST.in
README.md
pyproject.toml
setup.cfg
setup.py
botasaurus_requests/__init__.py
botasaurus_requests/__main__.py
botasaurus_requests/__version__.py
botasaurus_requests/cffi.py
botasaurus_requests/client.py
botasaurus_requests/cookies.py
botasaurus_requests/exceptions.py
botasaurus_requests/headers.py
botasaurus_requests/parser.py
botasaurus_requests/reqs.py
botasaurus_requests/request_class.py
botasaurus_requests/request_functions.py
botasaurus_requests/response.py
botasaurus_requests/session.py
botasaurus_requests/toolbelt.py
botasaurus_requests.egg-info/PKG-INFO
botasaurus_requests.egg-info/SOURCES.txt
botasaurus_requests.egg-info/dependency_links.txt
botasaurus_requests.egg-info/requires.txt
botasaurus_requests.egg-info/top_level.txt
botasaurus_requests/bin/__init__.py