Metadata-Version: 2.1
Name: botasaurus_requests
Version: 4.0.3
Summary: botasaurus_requests is a fork of the requests library with the playwright dependencies removed.
Author-email: Chetan <chetan@omkar.cloud>
License:                                  Apache License
Project-URL: Homepage, https://github.com/omkarcloud/botasaurus-requests
Keywords: tls,client,http,scraping,requests,humans
Classifier: Topic :: Internet :: WWW/HTTP
Classifier: Topic :: Internet :: WWW/HTTP :: Browsers
Classifier: Topic :: Software Development :: Libraries :: Python Modules
License-File: LICENSE
Requires-Dist: orjson
Requires-Dist: httpx
Requires-Dist: geventhttpclient
Requires-Dist: urllib3
Requires-Dist: rich
Requires-Dist: click
Requires-Dist: gevent
